mcp_reflect/__init__.py
mcp_reflect/evaluator.py
mcp_reflect/models.py
mcp_reflect/server.py
mcp_reflect-0.1.0.dist-info/LICENSE
mcp_reflect-0.1.0.dist-info/METADATA
mcp_reflect-0.1.0.dist-info/WHEEL
mcp_reflect-0.1.0.dist-info/entry_points.txt
mcp_reflect-0.1.0.dist-info/RECORD
