Metadata-Version: 2.3
Name: mcp-reflect
Version: 0.1.0
Summary: A framework for model self-reflection and meta-cognitive processing
License: MIT
Keywords: mcp,llm,ai,reflection,evaluation
Author: Jona Heidsick
Author-email: jona.heidsick@gmail.com
Requires-Python: >=3.11,<3.14
Classifier: Development Status :: 4 - Beta
Classifier: Intended Audience :: Developers
Classifier: License :: OSI Approved :: MIT License
Classifier: Programming Language :: Python :: 3
Classifier: Programming Language :: Python :: 3.11
Classifier: Programming Language :: Python :: 3.12
Classifier: Programming Language :: Python :: 3.13
Classifier: Topic :: Scientific/Engineering :: Artificial Intelligence
Requires-Dist: async-lru (>=2.0.4,<3.0.0)
Requires-Dist: fastmcp (>=2.0.0,<3.0.0)
Requires-Dist: pydantic (>=2.0.0)
Requires-Dist: uvicorn (>=0.23.0)
Project-URL: Repository, https://github.com/JonesH/mcp-reflect
